Metadata-Version: 2.4
Name: hanzo-tools-core
Version: 0.2.0
Summary: Core infrastructure for Hanzo tool packages
Author-email: Hanzo Industries Inc <dev@hanzo.ai>
License: MIT
Project-URL: Homepage, https://github.com/hanzoai/python-sdk
Project-URL: Bug Tracker, https://github.com/hanzoai/python-sdk/issues
Keywords: hanzo,tools,mcp,ai
Classifier: Programming Language :: Python :: 3
Classifier: License :: OSI Approved :: MIT License
Classifier: Operating System :: OS Independent
Requires-Python: >=3.12
Requires-Dist: mcp>=1.25.0
Requires-Dist: fastmcp>=2.14.1
Requires-Dist: pydantic>=2.12.5
Requires-Dist: typing-extensions>=4.13.0
Provides-Extra: dev
Requires-Dist: pytest>=7.0.0; extra == "dev"
Requires-Dist: ruff>=0.14.0; extra == "dev"
